torm_cache/TormCache.py
torm_cache/TormSerializer.py
torm_cache/__init__.py
torm_cache-0.1.12.dist-info/METADATA
torm_cache-0.1.12.dist-info/WHEEL
torm_cache-0.1.12.dist-info/RECORD
